[
  {
    "reviewer": "p*****5",
    "rating": 5,
    "comment": "Chất lượng sản phẩm:tốt\nĐúng với mô tả:đúng\n\nGiao nhanh, được gói kỹ lưỡng, đẹp. Cục sạc không có củ sạc đi kèm, mọi người mua riêng nhé",
    "date": "2026-02-05",
    "helpful": 0,
    "reply": ""
  },
  {
    "reviewer": "bluewater.nguyen",
    "rating": 5,
    "comment": "Đúng với mô tả:ok\nChất lượng sản phẩm:ok\n\nGiao hàng nhanh, hình thức giống như mô tả. Chức dùng nên chưa biết có được lâu không.",
    "date": "2026-04-13",
    "helpful": 0,
    "reply": ""
  },
  {
    "reviewer": "thitu0706",
    "rating": 5,
    "comment": "Đóng gói cẩn thận. Màu sp trong rất đẹp và chất liệu cũng xịn xò. Mình sạc đc 3 lần ip 15 promax.",
    "date": "2026-04-29",
    "helpful": 0,
    "reply": ""
  },
  {
    "reviewer": "nghia_tt",
    "rating": 5,
    "comment": "Sp đúng như mô tả, đẹp, cầm nặng tay",
    "date": "2026-02-04",
    "helpful": 0,
    "reply": ""
  },
  {
    "reviewer": "ha_th_9389",
    "rating": 5,
    "comment": "Giao hàng đúng sản phẩm, hình ảnh mang tính chất nhận xu, pin sạc rất nhanh và tiện lợi",
    "date": "2026-03-09",
    "helpful": 0,
    "reply": ""
  },
  {
    "reviewer": "p*****g",
    "rating": 5,
    "comment": "Nhận hàng nguyên seal, đúng miêu tả.\nSử dụng thời gian, đánh giá sau",
    "date": "2026-02-27",
    "helpful": 0,
    "reply": ""
  },
  {
    "reviewer": "t*****d",
    "rating": 5,
    "comment": "hỗ trợ khách hàng cực kỳ nhiệt tình.",
    "date": "2026-02-11",
    "helpful": 0,
    "reply": ""
  },
  {
    "reviewer": "hiephuong2019",
    "rating": 5,
    "comment": "Chất lượng sản phẩm:10\n\nShop đóng gói kỹ, giao đúng hẹn. Cục sạc cầm chắc tay. Màu đen rất đẹp sang. Có điều dùng cho Iphone 13 pro max thì phải tự cấm dây của mình vào cục sạc, này là do mình đọc không kỹ mô tả nên hiện tại thấy chưa tiện🥺",
    "date": "2026-03-26",
    "helpful": 0,
    "reply": ""
  },
  {
    "reviewer": "e*****7",
    "rating": 4,
    "comment": "",
    "date": "2026-03-11",
    "helpful": 0,
    "reply": ""
  },
  {
    "reviewer": "thunguyen3990",
    "rating": 5,
    "comment": "",
    "date": "2026-03-09",
    "helpful": 0,
    "reply": ""
  },
  {
    "reviewer": "ivynguyen3105",
    "rating": 5,
    "comment": "",
    "date": "2026-04-18",
    "helpful": 0,
    "reply": ""
  },
  {
    "reviewer": "little.boss1410",
    "rating": 5,
    "comment": "",
    "date": "2026-03-09",
    "helpful": 0,
    "reply": ""
  },
  {
    "reviewer": "anhmach77",
    "rating": 5,
    "comment": "",
    "date": "2026-04-23",
    "helpful": 0,
    "reply": ""
  },
  {
    "reviewer": "bienxanh76",
    "rating": 5,
    "comment": "",
    "date": "2026-04-04",
    "helpful": 0,
    "reply": ""
  },
  {
    "reviewer": "dragon_tf",
    "rating": 5,
    "comment": "",
    "date": "2026-02-11",
    "helpful": 0,
    "reply": ""
  },
  {
    "reviewer": "tuankaazin",
    "rating": 5,
    "comment": "",
    "date": "2026-03-29",
    "helpful": 0,
    "reply": ""
  },
  {
    "reviewer": "jimmycoconut88",
    "rating": 5,
    "comment": "",
    "date": "2026-03-17",
    "helpful": 0,
    "reply": ""
  },
  {
    "reviewer": "catim357849",
    "rating": 5,
    "comment": "",
    "date": "2026-02-05",
    "helpful": 0,
    "reply": ""
  },
  {
    "reviewer": "jh5804.choi",
    "rating": 5,
    "comment": "",
    "date": "2026-02-06",
    "helpful": 0,
    "reply": ""
  },
  {
    "reviewer": "l3gslkl_7g",
    "rating": 5,
    "comment": "",
    "date": "2026-02-08",
    "helpful": 0,
    "reply": ""
  },
  {
    "reviewer": "tbnhng538",
    "rating": 5,
    "comment": "",
    "date": "2026-02-09",
    "helpful": 0,
    "reply": ""
  },
  {
    "reviewer": "minhpro119",
    "rating": 5,
    "comment": "",
    "date": "2026-03-06",
    "helpful": 0,
    "reply": ""
  },
  {
    "reviewer": "giangthanhnguyet",
    "rating": 5,
    "comment": "",
    "date": "2026-03-05",
    "helpful": 0,
    "reply": ""
  },
  {
    "reviewer": "nhunnhun224",
    "rating": 5,
    "comment": "",
    "date": "2026-04-15",
    "helpful": 0,
    "reply": ""
  },
  {
    "reviewer": "v*****n",
    "rating": 5,
    "comment": "",
    "date": "2026-04-27",
    "helpful": 0,
    "reply": ""
  },
  {
    "reviewer": "baodungln",
    "rating": 5,
    "comment": "",
    "date": "2026-04-24",
    "helpful": 0,
    "reply": ""
  },
  {
    "reviewer": "cgzc0l0s8m",
    "rating": 5,
    "comment": "",
    "date": "2026-05-06",
    "helpful": 0,
    "reply": ""
  },
  {
    "reviewer": "phanminhthong",
    "rating": 1,
    "comment": "",
    "date": "2026-03-11",
    "helpful": 0,
    "reply": ""
  }
]